LICENSE
MANIFEST.in
README.rst
setup.py
daycare/.DS_Store
daycare/__init__.py
daycare/admin.py
daycare/cachekeys.py
daycare/dashboard_module.py
daycare/models.py
daycare/utils.py
daycare.egg-info/PKG-INFO
daycare.egg-info/SOURCES.txt
daycare.egg-info/dependency_links.txt
daycare.egg-info/not-zip-safe
daycare.egg-info/top_level.txt
daycare/middleware/.DS_Store
daycare/middleware/__init__.py
daycare/middleware/cmsmiddleware.py
daycare/middleware/redirecting.py
daycare/middleware/tracking.py
daycare/templates/.DS_Store
daycare/templates/daycare/.DS_Store
daycare/templates/daycare/dashboard_status_module.html